{
    "Loading_Section": {
        "Point Loading": {
            "name": "Point Loading",
            "Location": "POINT LOADING1.png",
            "modal": true,
            "Point Load": {
                "elementType": "input",
                "elementConfig": {
                    "type": "number",
                    "placeholder": "Enter the Point Load"
                },
                "value": "",
                "validation": {
                    "required": true
                },
                "valid": false,
                "label": "Point Load",
                "touched": false
            },
            "Distance from A": {
                "elementType": "input",
                "elementConfig": {
                    "type": "number",
                    "placeholder": "Enter the Distance from A"
                },
                "value": "",
                "validation": {
                    "required": true
                },
                "valid": false,
                "label": "Distance From A",
                "touched": false
            },
            "UDirection": {
                "elementType": "radio",
                "elementConfig": {
                    "type": "radio"
                },
                "value": "Up",
                "validation": {
                    "required": true
                },
                "valid": false,
                "label": "Up",
                "touched": false
            },
            "DDirection": {
                "elementType": "radio",
                "elementConfig": {
                    "type": "radio"
                },
                "value": "Down",
                "validation": {
                    "required": true
                },
                "valid": false,
                "label": "Down",
                "touched": false
            }
        },
        "Moment Loading": {
            "name": "Moment Loading",
            "Location": "MOMENT .png",
            "modal": true,
            "Point Moment": {
                "elementType": "input",
                "elementConfig": {
                    "type": "number",
                    "placeholder": "Enter the Point Load"
                },
                "value": "",
                "validation": {
                    "required": true
                },
                "valid": false,
                "label": "Point Moment",
                "touched": false
            },
            "Distance from A": {
                "elementType": "input",
                "elementConfig": {
                    "type": "number",
                    "placeholder": "Enter the Distance from A"
                },
                "value": "",
                "validation": {
                    "required": true
                },
                "valid": false,
                "label": "Distance From A",
                "touched": false
            },
            "UDirection": {
                "elementType": "radio",
                "elementConfig": {
                    "type": "radio"
                },
                "value": "Up",
                "validation": {
                    "required": true
                },
                "valid": false,
                "label": "Up",
                "touched": false
            },
            "DDirection": {
                "elementType": "radio",
                "elementConfig": {
                    "type": "radio"
                },
                "value": "Down",
                "validation": {
                    "required": true
                },
                "valid": false,
                "label": "Down",
                "touched": false
            }
        },
        "Uniform Distributed Load": {
            "name": "Uniform Distributed Load",
            "elementType": "image",
            "Location": "Uniform Loading.png",
            "modal": true,
            "Starting point of UDL from A": {
                "elementType": "input",
                "elementConfig": {
                    "type": "number",
                    "placeholder": "Enter the Point Load"
                },
                "value": "",
                "validation": {
                    "required": true
                },
                "label": "Starting point of UDL from A"
            },
            "Ending point of UDL from A": {
                "elementType": "input",
                "elementConfig": {
                    "type": "number",
                    "placeholder": "Enter the Distance from A"
                },
                "value": "",
                "validation": {
                    "required": true
                },
                "label": "Ending point of UDL from A",
                "touched": false
            },
            "Value of UDl": {
                "elementType": "input",
                "elementConfig": {
                    "type": "number",
                    "placeholder": "Enter the value of UDL"
                },
                "value": "",
                "validation": {
                    "required": true
                },
                "label": "Value of UDL",
                "touched": false
            },
            "UDirection": {
                "elementType": "radio",
                "elementConfig": {
                    "type": "radio"
                },
                "value": "Up",
                "validation": {
                    "required": true
                },
                "valid": false,
                "label": "Up",
                "touched": false
            },
            "DDirection": {
                "elementType": "radio",
                "elementConfig": {
                    "type": "radio"
                },
                "value": "Down",
                "validation": {
                    "required": true
                },
                "valid": false,
                "label": "Down",
                "touched": false
            }
        },
        "Trapezoidal Loading": {
            "name": "Trapezoidal Loading",
            "Location": "TRAPEZOIDAL LOADING.png",
            "modal": true,
            "Starting point of load from A": {
                "elementType": "input",
                "elementConfig": {
                    "type": "number",
                    "placeholder": "Enter the Point Load"
                },
                "value": "",
                "validation": {
                    "required": true
                },
                "label": "Starting point of UDL from A",
                "touched": false
            },
            "Ending point of load from A": {
                "elementType": "input",
                "elementConfig": {
                    "type": "number",
                    "placeholder": "Enter the Distance from A"
                },
                "value": "",
                "validation": {
                    "required": true
                },
                "label": "Ending point of UDL from A",
                "touched": false
            },
            "Starting Load": {
                "elementType": "input",
                "elementConfig": {
                    "type": "number",
                    "placeholder": "Enter the starting load"
                },
                "value": "",
                "validation": {
                    "required": true
                },
                "label": "Starting Load",
                "touched": false
            },
            "Ending Load": {
                "elementType": "input",
                "elementConfig": {
                    "type": "number",
                    "placeholder": "Enter the ending load"
                },
                "value": "",
                "touched": false,
                "validation": {
                    "required": true
                },
                "label": "Ending Load"
            },
            "UDirection": {
                "elementType": "radio",
                "elementConfig": {
                    "type": "radio"
                },
                "value": "Up",
                "validation": {
                    "required": true
                },
                "valid": false,
                "label": "Up",
                "touched": false
            },
            "DDirection": {
                "elementType": "radio",
                "elementConfig": {
                    "type": "radio"
                },
                "value": "Down",
                "validation": {
                    "required": true
                },
                "valid": false,
                "label": "Down",
                "touched": false
            }
        }
    }
}