{
    "Loading_Selection": [
        {
            "name": "Point Loading",
            "elementType": "image",
            "Location": "POINT LOADING1.png",
            "modal":true
        },
        {
            "name": "Moment Loading",
            "elementType": "image",
            "Location":"MOMENT .png",
            "modal":true
        },
        {
            "name": "Uniform Distributed Load",
            "elementType": "image",
            "Location": "Uniform Loading.png",
            "modal":true
        },
        {
            "name": "Trapezoidal Loading",
            "elementType": "image",
            "Location": "TRAPEZOIDAL LOADING.png",
            "modal":true
        }
    ]
}